<?xml version="1.0" encoding="UTF-8" standalone="no"?>
<OBJECT id="CollectionSplit">
   <ENTRY>
      <NAME>Type</NAME>
      <VALUES>
         <VALUE>
            <TYPE>name</TYPE>
            <SHALLBE>CollectionSplit</SHALLBE>
         </VALUE>
      </VALUES>
      <REQUIRED>false</REQUIRED>
      <INDIRECTREFRENCE>false</INDIRECTREFRENCE>
      <SINCEVERSION>2.0</SINCEVERSION>
      <DEPRECATEDIN/>
   </ENTRY>
   <ENTRY>
      <NAME>Direction</NAME>
      <VALUES>
         <VALUE>
            <TYPE>name</TYPE>
         </VALUE>
      </VALUES>
      <REQUIRED>false</REQUIRED>
      <INDIRECTREFRENCE>false</INDIRECTREFRENCE>
      <SINCEVERSION>2.0</SINCEVERSION>
      <DEPRECATEDIN/>
   </ENTRY>
   <ENTRY>
      <NAME>Position</NAME>
      <VALUES>
         <VALUE>
            <TYPE>number</TYPE>
         </VALUE>
      </VALUES>
      <REQUIRED>false</REQUIRED>
      <INDIRECTREFRENCE>false</INDIRECTREFRENCE>
      <SINCEVERSION>2.0</SINCEVERSION>
      <DEPRECATEDIN/>
   </ENTRY>
</OBJECT>
