<?xml version="1.0" encoding="UTF-8" standalone="no"?>
<OBJECT id="StandardLayoutAttributesColumn">
   <ENTRY>
      <NAME>Placement</NAME>
      <VALUES>
         <VALUE>
            <TYPE>name</TYPE>
         </VALUE>
      </VALUES>
      <REQUIRED>false</REQUIRED>
      <INDIRECTREFRENCE>false</INDIRECTREFRENCE>
      <SINCEVERSION>1.4</SINCEVERSION>
      <DEPRECATEDIN/>
   </ENTRY>
   <ENTRY>
      <NAME>WritingMode</NAME>
      <VALUES>
         <VALUE>
            <TYPE>name</TYPE>
         </VALUE>
      </VALUES>
      <REQUIRED>false</REQUIRED>
      <INDIRECTREFRENCE>false</INDIRECTREFRENCE>
      <SINCEVERSION>1.4</SINCEVERSION>
      <DEPRECATEDIN/>
   </ENTRY>
   <ENTRY>
      <NAME>BackgroundColor</NAME>
      <VALUES>
         <VALUE>
            <TYPE>array</TYPE>
            <VALIDATE/>
         </VALUE>
      </VALUES>
      <REQUIRED>false</REQUIRED>
      <INDIRECTREFRENCE>false</INDIRECTREFRENCE>
      <SINCEVERSION>1.5</SINCEVERSION>
      <DEPRECATEDIN/>
   </ENTRY>
   <ENTRY>
      <NAME>BorderColor</NAME>
      <VALUES>
         <VALUE>
            <TYPE>array</TYPE>
            <VALIDATE/>
         </VALUE>
      </VALUES>
      <REQUIRED>false</REQUIRED>
      <INDIRECTREFRENCE>false</INDIRECTREFRENCE>
      <SINCEVERSION>1.5</SINCEVERSION>
      <DEPRECATEDIN/>
   </ENTRY>
   <ENTRY>
      <NAME>BorderStyle</NAME>
      <VALUES>
         <VALUE>
            <TYPE>array</TYPE>
            <VALIDATE/>
         </VALUE>
         <VALUE>
            <TYPE>name</TYPE>
         </VALUE>
      </VALUES>
      <REQUIRED>false</REQUIRED>
      <INDIRECTREFRENCE>false</INDIRECTREFRENCE>
      <SINCEVERSION>1.5</SINCEVERSION>
      <DEPRECATEDIN/>
   </ENTRY>
   <ENTRY>
      <NAME>BorderThickness</NAME>
      <VALUES>
         <VALUE>
            <TYPE>array</TYPE>
            <VALIDATE/>
         </VALUE>
         <VALUE>
            <TYPE>number</TYPE>
         </VALUE>
      </VALUES>
      <REQUIRED>false</REQUIRED>
      <INDIRECTREFRENCE>false</INDIRECTREFRENCE>
      <SINCEVERSION>1.5</SINCEVERSION>
      <DEPRECATEDIN/>
   </ENTRY>
   <ENTRY>
      <NAME>Padding</NAME>
      <VALUES>
         <VALUE>
            <TYPE>array</TYPE>
            <VALIDATE/>
         </VALUE>
         <VALUE>
            <TYPE>number</TYPE>
         </VALUE>
      </VALUES>
      <REQUIRED>false</REQUIRED>
      <INDIRECTREFRENCE>false</INDIRECTREFRENCE>
      <SINCEVERSION>1.5</SINCEVERSION>
      <DEPRECATEDIN/>
   </ENTRY>
   <ENTRY>
      <NAME>Color</NAME>
      <VALUES>
         <VALUE>
            <TYPE>array</TYPE>
            <VALIDATE/>
         </VALUE>
      </VALUES>
      <REQUIRED>false</REQUIRED>
      <INDIRECTREFRENCE>false</INDIRECTREFRENCE>
      <SINCEVERSION>1.5</SINCEVERSION>
      <DEPRECATEDIN/>
   </ENTRY>
   <ENTRY>
      <NAME>ColumnCount</NAME>
      <VALUES>
         <VALUE>
            <TYPE>integer</TYPE>
         </VALUE>
      </VALUES>
      <REQUIRED>false</REQUIRED>
      <INDIRECTREFRENCE>false</INDIRECTREFRENCE>
      <SINCEVERSION>1.6</SINCEVERSION>
      <DEPRECATEDIN/>
   </ENTRY>
   <ENTRY>
      <NAME>ColumnGap</NAME>
      <VALUES/>
      <REQUIRED>false</REQUIRED>
      <INDIRECTREFRENCE>false</INDIRECTREFRENCE>
      <SINCEVERSION>1.6</SINCEVERSION>
      <DEPRECATEDIN/>
   </ENTRY>
   <ENTRY>
      <NAME>ColumnWidths</NAME>
      <VALUES/>
      <REQUIRED>false</REQUIRED>
      <INDIRECTREFRENCE>false</INDIRECTREFRENCE>
      <SINCEVERSION>1.6</SINCEVERSION>
      <DEPRECATEDIN/>
   </ENTRY>
</OBJECT>
